{
  "2015年圣诞节": {
    "009-Sec1Christmas2014": {
      "中文译文": "哦，哦！圣诞啦！蛋糕和火鸡，好好吃啊！啊嘞，瑞鹤？为啥生气了...欸...",
      "日文台词": "お、おーん、クリスマスね。ケーキ、七面鳥も、美味しいわー。あれっ？瑞鶴？何で怒ってんの？えっ",
      "档名": "009-Sec1Christmas2014",
      "编号": "009",
      "舰娘名字": "飞龙"
    }
  },
  "2016年三周年纪念": {
    "009-2ndAnniv": {
      "中文译文": "原来今天是庆祝日啊！太棒了！来年，也想和提督一起庆祝呢……呐♪",
      "日文台词": "そーか今日はお祝いなんだね！やったぁ！来年も、提督と一緒にお祝いしたい…ねっ♪",
      "档名": "009-2ndAnniv",
      "编号": "009",
      "舰娘名字": "飞龙"
    }
  },
  "2016年圣诞节": {
    "009-Sec1Christmas2014": {
      "中文译文": "哦，哦！圣诞啦！蛋糕和火鸡，好好吃啊！啊嘞，瑞鹤？为啥生气了...欸...",
      "日文台词": "お、おーん、クリスマスね。ケーキ、七面鳥も、美味しいわー。あれっ？瑞鶴？何で怒ってんの？えっ",
      "档名": "009-Sec1Christmas2014",
      "编号": "009",
      "舰娘名字": "飞龙"
    }
  },
  "2016年情人节": {
    "009-Sec1Valentine2016": {
      "中文译文": "哼哼♪，提督，送你巧克力哦巧克力♪好歹也是我亲手做的，要好好把它吃掉哦♪",
      "日文台词": "んっふ～♪　提督、チョコあげる、チョコ♪　一応手作りだよ？大事に食べてね♪",
      "档名": "009-Sec1Valentine2016",
      "编号": "009",
      "舰娘名字": "飞龙"
    }
  },
  "2016年新年季节": {
    "009-Sec1Shinnen2015": {
      "中文译文": "新年快乐！提督，今年也请多多关照二航战呢！呢！",
      "日文台词": "明けましておめでとうございまーす！ 提督、今年も二航戦をよろしくね！ ねっ！",
      "档名": "009-Sec1Shinnen2015",
      "编号": "009",
      "舰娘名字": "飞龙"
    }
  },
  "2016年秋刀鱼祭典": {
    "009-Sec1Sanma2016": {
      "中文译文": "哼哼……盐烧秋刀鱼好闻的味道！对啊，原来是到了镇守府秋刀鱼祭的时节了！真棒啊！",
      "日文台词": "クンクン…秋刀魚の塩焼きのいい匂い！そうか、鎮守府秋刀魚祭りの季節！いいね！",
      "档名": "009-Sec1Sanma2016",
      "编号": "009",
      "舰娘名字": "飞龙"
    }
  },
  "2017年四周年纪念": {
    "009-Sec1FourthAnniversary": {
      "中文译文": "太棒了，四周年！这不是很厉害吗！恭喜啦，提督和我们！耶！",
      "日文台词": "やったぁ、四周年！すーごいじゃない！おめでとう、提督と私たち！イェイ！",
      "档名": "009-Sec1FourthAnniversary",
      "编号": "009",
      "舰娘名字": "飞龙"
    }
  },
  "2017年情人节": {
    "009-Sec1Valentine2016": {
      "中文译文": "哼哼♪，提督，送你巧克力哦巧克力♪好歹也是我亲手做的，要好好把它吃掉哦♪",
      "日文台词": "んっふ～♪　提督、チョコあげる、チョコ♪　一応手作りだよ？大事に食べてね♪",
      "档名": "009-Sec1Valentine2016",
      "编号": "009",
      "舰娘名字": "飞龙"
    }
  },
  "2017年新年季节": {
    "009-Sec1Shinnen2015": {
      "中文译文": "新年快乐！提督，今年也请多多关照二航战呢！呢！",
      "日文台词": "明けましておめでとうございまーす！ 提督、今年も二航戦をよろしくね！ ねっ！",
      "档名": "009-Sec1Shinnen2015",
      "编号": "009",
      "舰娘名字": "飞龙"
    }
  },
  "2017年秋刀鱼祭典": {
    "009-Sec1Sanma2016": {
      "中文译文": "哼哼……盐烧秋刀鱼好闻的味道！对啊，原来是到了镇守府秋刀鱼祭的时节了！真棒啊！",
      "日文台词": "クンクン…秋刀魚の塩焼きのいい匂い！そうか、鎮守府秋刀魚祭りの季節！いいね！",
      "档名": "009-Sec1Sanma2016",
      "编号": "009",
      "舰娘名字": "飞龙"
    }
  },
  "2017年节分季节": {
    "009-Sec1Setsubunn2017": {
      "中文译文": "是节分呢，真不错！扮鬼的是……加贺？！是谁定的人选啦……提督？还是赤城？",
      "日文台词": "節分ね。いいじゃない？鬼は…加賀さんか！誰よ決めた人…提督？赤城さん？",
      "档名": "009-Sec1Setsubunn2017",
      "编号": "009",
      "舰娘名字": "飞龙"
    }
  },
  "2018年五周年纪念": {
    "009-Sec1FifthAnniversary": {
      "中文译文": "太好了，又是纪念日。挺厉害嘛。谢谢提督，也祝贺我们！耶ー！",
      "日文台词": "やった、また記念の日。すごいじゃない。ありがとう提督、おめでとう、私たち！イエーイ！",
      "档名": "009-Sec1FifthAnniversary",
      "编号": "009",
      "舰娘名字": "飞龙"
    }
  },
  "2018年新年季节": {
    "009-Sec1Shinnen2015": {
      "中文译文": "新年快乐！提督，今年也请多多关照二航战呢！呢！",
      "日文台词": "明けましておめでとうございまーす！ 提督、今年も二航戦をよろしくね！ ねっ！",
      "档名": "009-Sec1Shinnen2015",
      "编号": "009",
      "舰娘名字": "飞龙"
    }
  },
  "2周年纪念": {
    "009-2ndAnniv": {
      "中文译文": "对了今天是庆典呢，明年也想和提督一起庆祝呢～",
      "日文台词": "そうか今日はお祝いなんだね？やったぁ～♪来年も、提督と一緒にお祝いしたい、ね？",
      "档名": "009-2ndAnniv",
      "编号": "009",
      "舰娘名字": "飞龙"
    }
  }
}