{
  "2017年盛夏季节": {
    "037-Sec1Manatsu2016": {
      "file": "/6/62/037-Sec1Manatsu2016.mp3",
      "ja": "ふぅ、今年も夏をどうにか乗り越えられそう。司令官、感謝です。はい！",
      "vname": "秘书舰1",
      "zh": "呼，今年似乎也能顺利跨越这个夏天呢。司令官，非常感谢，嗯！"
    }
  },
  "2018年情人节": {
    "037-Sec1Valentine2016": {
      "file": "/1/1b/037-Sec1Valentine2016.mp3",
      "ja": "司令官、まだ見ちゃダメです！もう少し、待っててくださいね。三日月特製のチョコケーキ、もうすぐ完成ですから！",
      "vname": "秘书舰1",
      "zh": "司令官！现在不要偷看啊！请在等一下吧。三日月我特制的巧克力蛋糕马上就能做好了！"
    }
  },
  "2018年新年季节": {
    "037-Sec1Shinnen2016": {
      "file": "/8/82/037-Sec1Shinnen2016.mp3",
      "ja": "新年あけましておめでとうございます。司令官、今年もよろしくお願いしますね。",
      "vname": "秘书舰1",
      "zh": "新年快乐。司令官，今年也请多关照了。"
    }
  }
}