{
  "2017年年末大扫除": {
    "069-Sec1Nenmatsu2015": {
      "中文译文": "诶——，这年也快到年末了啊，真没办法。主人也一起打扫吧！",
      "日文台词": "えー…今年も年末になってしまいましたが～…まぁ仕方ない。ご主人様も、掃除掃除っと！",
      "档名": "069-Sec1Nenmatsu2015",
      "编号": "069a",
      "舰娘名字": "涟改"
    }
  },
  "2018年冬季活动决战前夜": {
    "069-Sec1EveOfBattle2018": {
      "中文译文": "怎么了，主人?",
      "日文台词": "どうしたの、ご主人さま？",
      "档名": "069-Sec1EveOfBattle2018",
      "编号": "069a",
      "舰娘名字": "涟改"
    }
  },
  "2018年初夏季节": {
    "069a-Sec1EveOfBattle2018": {
      "中文译文": "",
      "日文台词": "",
      "档名": "069a-Sec1EveOfBattle2018",
      "编号": "069a",
      "舰娘名字": "涟改"
    }
  },
  "2018年情人节": {
    "069-Sec1Valentine2016": {
      "中文译文": "情人节(゜∀゜)来了！没办法……今年也要把大~巧克力，给主人❤",
      "日文台词": "バレンタイン(゜∀゜)キタコレ！　仕方ない…今年はご主人様にもおおーきなチョコ、あげる❤",
      "档名": "069-Sec1Valentine2016",
      "编号": "069a",
      "舰娘名字": "涟改"
    }
  },
  "2018年新年季节": {
    "069-Sec1Shinnen2015": {
      "中文译文": "新年(ﾟ∀ﾟ)来啦！！啊啊，今年又老了一岁啊",
      "日文台词": "新年(ﾟ∀ﾟ)ｷﾀｺﾚ!!ああ、今年も一年歳を取てしまいましたが",
      "档名": "069-Sec1Shinnen2015",
      "编号": "069a",
      "舰娘名字": "涟改"
    }
  }
}