{
  "2015年圣诞节": {
    "084-Sec1Christmas2015": {
      "中文译文": "啥？什么鬼？圣诞？啊啊啊，这些冬季节日是搞什么啊，也算我一个啊！",
      "日文台词": "うん？何だって？メリクリだ？かあー！何だ、その冬祭りは！アタイも混ぜろって！",
      "档名": "084-Sec1Christmas2015",
      "编号": "084",
      "舰娘名字": "凉风"
    }
  },
  "2015年梅雨季节": {
    "084-Tsuyu2015": {
      "中文译文": "嗯……梅雨季啊。下雨天我倒是不讨厌啦。对吧？五月雨！",
      "日文台词": "う～ん、梅雨だな。雨かあ、嫌いじゃねえけど…なっ五月雨、なあ！",
      "档名": "084-Tsuyu2015",
      "编号": "084",
      "舰娘名字": "凉风"
    }
  },
  "2015年盛夏季节": {
    "084-Seika2015": {
      "中文译文": "来了来了这个季节最棒啦！果然我还是喜欢夏天啊~感觉不错！",
      "日文台词": "キタキタこの季節最高だぜ！やばあたいは夏が好きだな～いい感じだぜ！",
      "档名": "084-Seika2015",
      "编号": "084",
      "舰娘名字": "凉风"
    }
  },
  "2016年三周年纪念": {
    "084-Sec12ndAnniv": {
      "中文译文": "你说啥呢！今天是超级重要的日子啊！提督恭喜啊！",
      "日文台词": "てやんでぇー！今日はすっげぇ大切な日じゃねぇか。提督、おめでとさん！なん！",
      "档名": "084-Sec12ndAnniv",
      "编号": "084",
      "舰娘名字": "凉风"
    }
  },
  "2016年圣诞节": {
    "084-Sec1Christmas2015": {
      "中文译文": "啥？什么鬼？圣诞？啊啊啊，这些冬季节日是搞什么啊，也算我一个啊！",
      "日文台词": "うん？何だって？メリクリだ？かあー！何だ、その冬祭りは！アタイも混ぜろって！",
      "档名": "084-Sec1Christmas2015",
      "编号": "084",
      "舰娘名字": "凉风"
    }
  },
  "2016年梅雨季节": {
    "084-Sec1Tsuyu2015": {
      "中文译文": "嗯……梅雨季啊。下雨天我倒是不讨厌啦。对吧？五月雨！",
      "日文台词": "う～ん、梅雨だな。雨かあ、嫌いじゃねえけど…なっ五月雨、なあ！",
      "档名": "084-Sec1Tsuyu2015",
      "编号": "084",
      "舰娘名字": "凉风"
    }
  },
  "2016年盛夏季节": {
    "084-Seika2015": {
      "中文译文": "来了来了这个季节最棒啦！果然我还是喜欢夏天啊~感觉不错！",
      "日文台词": "キタキタこの季節最高だぜ！やばあたいは夏が好きだな～いい感じだぜ！",
      "档名": "084-Seika2015",
      "编号": "084",
      "舰娘名字": "凉风"
    }
  },
  "2017年四周年纪念": {
    "084-Sec12ndAnniv": {
      "中文译文": "今天是相当重要得日子不是嘛～提督，恭喜啦～呐～",
      "日文台词": "てやんでい！今日はすっげえ大切な日じゃねえか！提督、おめっとさん！なあっ！",
      "档名": "084-Sec12ndAnniv",
      "编号": "084",
      "舰娘名字": "凉风"
    }
  },
  "2017年梅雨季节": {
    "084-Sec1Tsuyu2015": {
      "中文译文": "嗯……梅雨季啊。下雨天我倒是不讨厌啦。对吧？五月雨！",
      "日文台词": "う～ん、梅雨だな。雨かあ、嫌いじゃねえけど…なっ五月雨、なあ！",
      "档名": "084-Sec1Tsuyu2015",
      "编号": "084",
      "舰娘名字": "凉风"
    }
  },
  "2周年纪念": {
    "084-Sec12ndAnniv": {
      "中文译文": "今天是相当重要得日子不是嘛～提督，恭喜啦～呐～",
      "日文台词": "てやんでい！今日はすっげえ大切な日じゃねえか！提督、おめっとさん！なあっ！",
      "档名": "084-Sec12ndAnniv",
      "编号": "084",
      "舰娘名字": "凉风"
    }
  }
}