{
  "2017年年末大扫除": {
    "020-Sec1Nenmatsu2014": {
      "中文译文": "哇……已经到年末了啊~ 镇守府大扫除压根儿就还开始……唉。",
      "日文台词": "うひーもう年末だよ～。　鎮守府も大掃除とか全然まだじゃーん。うひー",
      "档名": "020-Sec1Nenmatsu2014",
      "编号": "115",
      "舰娘名字": "北上改二"
    }
  },
  "2018年情人节": {
    "020-Sec1Valentine2016": {
      "中文译文": "情人节啊~......为什么我会收到巧克力呢？是这样的日子么？",
      "日文台词": "バレンタインね～……なんであたしチョコ貰うんだろ？　そういう日だっけ？",
      "档名": "020-Sec1Valentine2016",
      "编号": "115",
      "舰娘名字": "北上改二"
    }
  },
  "2018年新年季节": {
    "020-Sec1Shinnen2015": {
      "中文译文": "呀，好高兴呀，今年也请多关照了啊。正月果然还是想悠闲一点儿啊。是吧，大井亲~",
      "日文台词": "や～めでたいね。今年もよろしくね。正月ぐらいはのんびりしたいね。ね～おっいち～",
      "档名": "020-Sec1Shinnen2015",
      "编号": "115",
      "舰娘名字": "北上改二"
    }
  }
}