{
  "2018年冬季活动决战前夜": {
    "168a-Sec2Valentine2018": {
      "中文译文": "滨风，舰队现在，状态怎么样？",
      "日文台词": "浜風、艦隊の塩梅は、どがいなんね？",
      "档名": "168a-Sec2Valentine2018",
      "编号": "168a",
      "舰娘名字": "浦风改"
    }
  },
  "2018年情人节": {
    "168a-Sec2Valentine2018": {
      "中文译文": "滨风，舰队现在，状态怎么样？",
      "日文台词": "浜風、艦隊の塩梅は、どがいなんね？",
      "档名": "168a-Sec2Valentine2018",
      "编号": "168a",
      "舰娘名字": "浦风改"
    }
  },
  "2018年新年季节": {
    "168-Sec1Shinnen2015": {
      "中文译文": "提督，恭贺新年啊。今年也请多指教了",
      "日文台词": "提督、謹賀新年じゃけえ。今年もよろしゅうね！",
      "档名": "168-Sec1Shinnen2015",
      "编号": "168a",
      "舰娘名字": "浦风改"
    }
  }
}