{
  "2017年年末大扫除": {
    "087-Sec1Nenmatsu2015": {
      "file": "/7/73/087-Sec1Nenmatsu2015.mp3",
      "ja": "よーっし！何か乗り越えた気がする！気持ち切り替えて、年末大掃除よ！四駆！八駆！みんな集合よ！大掃除、全力でいくわ！",
      "vname": "秘书舰1",
      "zh": "哟西！好像感到了跨越的力量！改变心情，年末大扫除！四驱，八驱，集合！全力大扫除！"
    }
  },
  "2018年冬季活动决战前夜": {
    "289-Sec2Valentine2018": {
      "file": "/2/26/289-Sec2Valentine2018.mp3",
      "ja": "今はやってあげるわ！しかも全力で！第二十四駆逐隊、出撃します！",
      "vname": "秘书舰2",
      "zh": "我就帮你一把吧，用我的全力！第二十四驱逐队，出击！"
    }
  },
  "2018年情人节": {
    "087-Sec1Valentine2016": {
      "file": "/4/41/087-Sec1Valentine2016.mp3",
      "ja": "司令官……あの……義理よ、義理。完全に義理なんだから！　はい、一応、終わり！",
      "vname": "秘书舰1",
      "zh": "司令官...这个...是义理的啦，义理的！完完全全就是义理的啦！来，也算是，结束啦！"
    },
    "289-Sec2Valentine2018": {
      "file": "/2/26/289-Sec2Valentine2018.mp3",
      "ja": "今はやってあげるわ！しかも全力で！第二十四駆逐隊、出撃します！",
      "vname": "秘书舰2",
      "zh": "我就帮你一把吧，用我的全力！第二十四驱逐队，出击！"
    }
  },
  "2018年新年季节": {
    "087-Sec1Shinnen2016": {
      "file": "/5/5e/087-Sec1Shinnen2016.mp3",
      "ja": "新しい年が…司令官。一応いておくけど。今年もよろしく。…そ、それだけよ！",
      "vname": "秘书舰1",
      "zh": "又到新的一年了呢……司令官，姑且算是跟你说一声，今年也请多指教……只，只有这个啦！"
    }
  }
}