{
  "2017年初夏季节": {
    "317-Sec1Shoka2017": {
      "中文译文": "小国，夏天的准备万全了的说？诶？还在烦恼吗？身为海防舰最重要的就是要做事干脆的说！就是这样的说！这样就可以了咻！",
      "日文台词": "クナー、夏の準備はばっちりっす？え？まだ悩んでいるっすか？海防艦は思い切りが大事っすよ！そうっす！それでいいっしゅ！",
      "档名": "317-Sec1Shoka2017",
      "编号": "317",
      "舰娘名字": "占守"
    }
  },
  "2017年梅雨季节": {
    "317-Sec1Tsuyu2017": {
      "中文译文": "小国，今天也下雨的说！呃……诶？你在做什么呢？挺熟练的说。是司令的布偶玩具么？干嘛瞪我啦？不是么咻？",
      "日文台词": "クナー、今日も雨っす。…で、あれ、何してるっす？ …なかなか器用っす。司令のぬいぐるみっすか？わ、なんで睨んでるっす？違うっしゅ？",
      "档名": "317-Sec1Tsuyu2017",
      "编号": "317",
      "舰娘名字": "占守"
    }
  },
  "2018年五周年纪念": {
    "317-Sec1FifthAnniversary": {
      "中文译文": "司令，不得了了咻！祝贺五周年！占守我们是一周年。舰队是五周年咻！",
      "日文台词": "司令、やばいしゅ！五周年のお祝いっす！占守たちは一周年。艦隊は五周年しゅ！",
      "档名": "317-Sec1FifthAnniversary",
      "编号": "317",
      "舰娘名字": "占守"
    }
  },
  "2018年初春季节": {
    "317-Sec1Haru2018": {
      "中文译文": "是赏花的季节了！樱花真好啊。小国、小垣、小八、司令！赏花突击！小垣、小八，要做很多好吃的咻！",
      "日文台词": "お花見の季節っす！桜はすばらしいっす。クナ、ガキ、ハチ、しれぇ！お花見に突撃っす！ガキ、ハチ！おいしいのいっぱい作るしゅ！",
      "档名": "317-Sec1Haru2018",
      "编号": "317",
      "舰娘名字": "占守"
    }
  },
  "2018年梅雨季节": {
    "317a-Sec1Tsuyu2017": {
      "中文译文": "小国，今天也下雨的说！呃……诶？你在做什么呢？挺熟练的说。是司令的布偶玩具么？干嘛瞪我啦？不是么咻？",
      "日文台词": "クナー、今日も雨っす。…で、あれ、何してるっす？ …なかなか器用っす。司令のぬいぐるみっすか？わ、なんで睨んでるっす？違うっしゅ？",
      "档名": "317a-Sec1Tsuyu2017",
      "编号": "317",
      "舰娘名字": "占守"
    }
  },
  "2018年白色情人节": {
    "317-Sec1WhiteDay2018": {
      "中文译文": "司令，感谢你的回礼~稍微有点自豪呢~真好呢，回礼~呜嘻嘻……",
      "日文台词": "しれぇ、お返しありがとうっす。ちょっと自慢っす。うひひ、いいっすね、お返し。うひひ…",
      "档名": "317-Sec1WhiteDay2018",
      "编号": "317",
      "舰娘名字": "占守"
    }
  }
}