{
  "2017年初秋季节": {
    "318a-Sec1Shoshuu2017": {
      "file": "/6/67/318a-Sec1Shoshuu2017.mp3",
      "ja": "あ、阿武隈さん！はい、元気です！秋祭りですよね？ご一緒にどうですか？あぁ、そうですか。了解です。また今度、是非♪",
      "vname": "秘书舰1",
      "zh": "啊，阿武隈！嗯，我很好！是秋季庙会对吧？一起去怎么样？啊，这样啊。明白了。那下次请一定要约我啊。"
    }
  },
  "2017年年末大扫除": {
    "318a-Sec1Nenmatsu2017": {
      "file": "/b/b1/318a-Sec1Nenmatsu2017.mp3",
      "ja": "妹たち集まって〜姉さんが大掃除って騒ぐ季節だから、私たち先に用意しとこう！はっ、うん！さすが、わかってるね、ありがとう！",
      "vname": "秘书舰1",
      "zh": "妹妹们集合~姐姐说这是个大扫除的忙碌季，我们要准备起来！啊，嗯！不错，都明白了呢，谢谢！"
    }
  },
  "2018年情人节": {
    "318a-Sec1Valentine2018": {
      "file": "/3/34/318a-Sec1Valentine2018.mp3",
      "ja": "ふっふーん、教えてもらってしまったぁ♪ 特製チョコケーキのレシピ！ あたしも作るんだぁ！ 待ってろー司令！ 姉さん！ 神風さーん！",
      "vname": "秘书舰1",
      "zh": "嘿嘿~我学会这招啦♪ 特制巧克力蛋糕的菜谱！我也来做！等着哦，司令！姐姐！神风！"
    }
  },
  "2018年新年季节": {
    "318a-Sec1Shinnen2018": {
      "file": "/1/11/318a-Sec1Shinnen2018.mp3",
      "ja": "あっ、姉さん待って待って。ふぅ、追いついた。司令、皆、今年もよろしくね。明けましておめでとうございます。",
      "vname": "秘书舰1",
      "zh": "啊，姐姐等等。呼，追上了。司令，各位，今年也请多指教。新年快乐。"
    }
  },
  "2018年节分季节": {
    "318a-Sec1Setubunn2018": {
      "file": "/0/06/318a-Sec1Setubunn2018.mp3",
      "ja": "おっ、子日さん、今年鬼役なんですか？では、仕方ないですね。力一杯、行かせて頂きます。え～夾叉！次は当てます！",
      "vname": "秘书舰1",
      "zh": "噢？子日，今年要扮鬼吗？那就没办法了。我可要全力以赴的噢！嘿！交叉！下次就要打中你了！"
    }
  }
}