{
  "2021年万圣节": {
    "477-Sec1Halloween2021": {
      "file": "/4/4a/477-Sec1Halloween2021.mp3",
      "ja": "ワシのモットーゥは、誰にも負けないっ！ もちろん、サンママッツーリも、誰にも負けないぞ！ 征くぞ！",
      "vname": "秘书舰1",
      "zh": "本宫的格言是，不会输给任何人！不用说，秋刀鱼祭典也是，不会输给任何人！上阵吧！"
    }
  },
  "2021年初秋季节": {
    "477-Sec1Shoshuu2021": {
      "file": "/c/c4/477-Sec1Shoshuu2021.mp3",
      "ja": "いや、なんか楽しそう！ ワシも行っていいか？ 鎮守府秋祭り。",
      "vname": "秘书舰1",
      "zh": "咦，总觉得看起来很高兴!本宫也可以去吗?镇守府秋祭."
    },
    "477-Sec2Shoshuu2021": {
      "file": "/c/c8/477-Sec2Shoshuu2021.mp3",
      "ja": "屋台の食べ物、美味しそうだ！ ……試して、いいか？",
      "vname": "秘书舰2",
      "zh": "小摊的食物，看起来真好吃！……本宫也，可以试试吗？"
    },
    "477-Sec3Shoshuu2021": {
      "file": "/f/f0/477-Sec3Shoshuu2021.mp3",
      "ja": "えっと……キモノ？ あ、そうか。ユカタだ！ なんかいいなあ！……どう……かな？",
      "vname": "秘书舰3",
      "zh": "那个……和服？啊，这样啊。是浴衣啊！感觉不错呢！……怎……么样？"
    }
  },
  "2022年九周年纪念": {
    "477-Sec1NinthAnniversary": {
      "file": "/6/60/477-Sec1NinthAnniversary.mp3",
      "ja": "ん？艦隊は九周年？マジか？まあ、わしの艦歴に比べれば…そういうことではない？分かった。お祝いしよう！年代物のワインをかけて、乾杯！",
      "vname": "秘书舰1",
      "zh": "嗯？舰队九周年？真的？嗨，跟老身的舰历还是没得比……没什么好比的？好吧。总之来庆祝吧！这可是陈年红酒！干杯！"
    }
  },
  "2022年情人节": {
    "477-Sec1Valentine2022": {
      "file": "/8/8e/477-Sec1Valentine2022.mp3",
      "ja": "バレンタイン……まさに……た、沢山の敵。……だが、誰にも負けないっ！提督！ ……わ、ワシの弩級チョコ……あげる……。",
      "vname": "秘书舰1",
      "zh": "情人节……敌人不可谓不多……但是，老朽不会输给任何人！提督！……老朽的无畏舰级巧克力……给你吃……"
    }
  },
  "2022年新年季节": {
    "477-Sec1Shinnen2022": {
      "file": "/7/71/477-Sec1Shinnen2022.mp3",
      "ja": "提督、新年だ。今年もワシは誰にも負けない！ の精神で行こうと思う。アンタらも……そうだな、誰にも負けない！ ……知ってる。今年も頑張ろう！",
      "vname": "秘书舰1",
      "zh": "提督，新年了。今年老朽也打定主意不会输给任何人！。你也……不会输给任何人！我知道。今年也加油吧！"
    }
  },
  "2022年节分季节": {
    "477-Sec1Setubunn2022": {
      "file": "/d/d2/477-Sec1Setubunn2022.mp3",
      "ja": "噂のセッツブーン！ だな！ ワシの裏モットー、教えよか？「沢山の敵、マジ、うぜー！」だよ。まさに、セッツブーン！！",
      "vname": "秘书舰1",
      "zh": "传说中的jiefen！是吧！要听听，本宫的隐藏格言么？是「那么多敌人，真的，很烦！」哦。恰好是，jiefen！！"
    }
  }
}