{
  "2022年圣诞节": {
    "505-Sec1Christmas2022": {
      "file": "/d/d7/505-Sec1Christmas2022.mp3",
      "ja": "鎮守府でのクリスマス、いいですね。あ、さどちゃん、ケーキ1人で欲張りすぎじゃん。お腹壊すよ。でもケーキ本当美味しい。甘くて美味しい。",
      "vname": "秘书舰1",
      "zh": "镇守府的圣诞节真好啊。啊，佐渡，蛋糕吃太多，会吃坏肚子的。不过蛋糕真好吃啊。甜甜的，真好吃。"
    }
  },
  "2022年盛夏季节": {
    "505-Sec1Seika2022": {
      "file": "/e/ee/505-Sec1Seika2022.mp3",
      "ja": "今年も、夏が近づいて来ました。提督は夏が近づくと、どんな思いになりますか？倉橋は…あ、いえ、何でもありません。倉橋、頑張ります！",
      "vname": "秘书舰1",
      "zh": "今年也快入夏了。提督每年这时都有些什么想法呢？仓桥会想……没事，请别在意。仓桥会加油的！"
    }
  },
  "2022年秋刀鱼祭典": {
    "505-Sec1Sanma2022": {
      "file": "/a/a5/505-Sec1Sanma2022.mp3",
      "ja": "提督、秋刀魚ですか？ 了解です。秋刀魚も、この倉橋にお任せください。えっと……あっ、敷波さん。色々と教えて下さい。頑張ります！",
      "vname": "秘书舰1",
      "zh": "提督，是秋刀鱼吗？明白了。秋刀鱼也，交个我仓桥吧。那个……啊，敷波小姐。我有很多事情想向你请教。我会加油的！"
    }
  }
}